{"tube_length": 2.0, "tube_radius": 0.1, "tube_thickness": 0.01, "tube_material": "fibre_carbon", "tube_density": 1780.0, "nose_type": "ellipse", "nose_parameter": 0.0, "nose_length": 0.5, "nose_radius": 0.1, "nose_thickness": 0.01, "nose_material": "acier", "nose_density": 7850.0, "fins_Cr": 0.2, "fins_Ct": 0.1, "fins_Xt": 0.1, "fins_s": 0.15, "fins_thickness": 0.01, "fins_number": 4, "fins_material": "fibre_carbon", "fins_density": 1780.0, "fins_position": 0.0, "motor": {"availability": "OOP", "avgThrustN": 2.48, "burnTimeS": 0.23, "certOrg": "National Association of Rocketry", "commonName": "1/4A2", "dataFiles": 2, "delays": "2,4", "designation": "1/4A2", "diameter": 10.5, "impulseClass": "A", "infoUrl": "http://nar.org/SandT/pdf/Apogee/qtrA2.pdf", "length": 38, "manufacturer": "Apogee Components", "manufacturerAbbrev": "Apogee", "maxThrustN": 5.4, "motorId": "5f4294d20002310000000003", "propWeightG": 0.76, "samples": [[0.0, 0], [0.02, 250], [0.04, 210], [0.62, 160], [0.66, 150], [0.68, 142], [0.8, 62], [0.84, 48], [0.88, 34], [0.92, 24], [0.96, 15], [1.0, 10]], "totImpulseNs": 0.57, "type": "SU", "updatedOn": "2019-04-17"}, "motor_position": 0.0, "motor_ring": true, "motor_ring_material": "acier", "motor_ring_density": 7850.0, "additional_masses": [], "rocket_volume": 0.03971458694481574, "rocket_mass": 1639, "rocket_cog": [1.0565431692766574, 0.0, 0.0], "rocket_inertia": [[0.3915189535044366, 0.0, 0.0], [0.0, 104.03647709138833, 0.0], [0.0, 0.0, 104.03647709236026]]}